Metadata-Version: 2.1
Name: gbp
Version: 0.9.37
Summary: Suite to help with Debian packages in Git repositories
Home-page: https://honk.sigxcpu.org/piki/projects/git-buildpackage/
Author: Guido Günther
Author-email: agx@sigxcpu.org
License: GPLv2-or-later
Classifier: Environment :: Console
Classifier: Programming Language :: Python :: 3
Classifier: Topic :: Software Development :: Version Control
Classifier: Operating System :: POSIX :: Linux
Requires-Python: >=3.11
License-File: COPYING
Requires-Dist: python-dateutil
Requires-Dist: importlib-metadata; python_version < "3.8"
